vref_util/__init__.py
vref_util/verse.py
vref_util/verse_list.py
vref_util/versification.py
vref_util/vref.py
vref_util/vref.txt
vref_util-0.0.5.dist-info/LICENSE
vref_util-0.0.5.dist-info/METADATA
vref_util-0.0.5.dist-info/WHEEL
vref_util-0.0.5.dist-info/top_level.txt
vref_util-0.0.5.dist-info/RECORD
