Metadata-Version: 2.1
Name: vref_util
Version: 0.0.5
Summary: Tools to work with vref files (e.g., in the ebible corpus)
Home-page: https://github.com/jcuenod/vref_util
Author: James Cuénod
Author-email: j3frea+github@gmail.com
License: MIT
Classifier: Programming Language :: Python :: 3
Classifier: License :: OSI Approved :: MIT License
Classifier: Operating System :: OS Independent
Requires-Python: >=3.8
License-File: LICENSE
